todoist_helper/__init__.py
todoist_helper/add_obsidian_task.py
todoist_helper/add_todoist_task.py
todoist_helper/base.py
todoist_helper/main.py
todoist_helper/utils.py
todoist_helper-0.0.3.dist-info/entry_points.txt
todoist_helper-0.0.3.dist-info/LICENSE
todoist_helper-0.0.3.dist-info/WHEEL
todoist_helper-0.0.3.dist-info/METADATA
todoist_helper-0.0.3.dist-info/RECORD
